qiime_2_ll_quick_viewer/__init__.py
qiime_2_ll_quick_viewer/cli.py
qiime_2_ll_quick_viewer/qiime_2_ll_quick_viewer.py
qiime_2_ll_quick_viewer-0.2.8.dist-info/DESCRIPTION.rst
qiime_2_ll_quick_viewer-0.2.8.dist-info/METADATA
qiime_2_ll_quick_viewer-0.2.8.dist-info/RECORD
qiime_2_ll_quick_viewer-0.2.8.dist-info/WHEEL
qiime_2_ll_quick_viewer-0.2.8.dist-info/entry_points.txt
qiime_2_ll_quick_viewer-0.2.8.dist-info/metadata.json
qiime_2_ll_quick_viewer-0.2.8.dist-info/top_level.txt
