Metadata-Version: 2.0
Name: qiime-2-ll-quick-viewer
Version: 0.2.8
Summary: Ley Lab Quick Viewer for Qiime 2 artifacts.
Home-page: https://github.com/leylabmpi/qiime_2_ll_quick_viewer
Author: Guillermo Luque
Author-email: guillermo.luque.ds@gmail.com
License: MIT license
Keywords: qiime_2_ll_quick_viewer
Platform: UNKNOWN
Classifier: Development Status :: 2 - Pre-Alpha
Classifier: Intended Audience :: Developers
Classifier: License :: OSI Approved :: MIT License
Classifier: Natural Language :: English
Classifier: Programming Language :: Python :: 2
Classifier: Programming Language :: Python :: 2.6
Classifier: Programming Language :: Python :: 2.7
Classifier: Programming Language :: Python :: 3
Classifier: Programming Language :: Python :: 3.3
Classifier: Programming Language :: Python :: 3.4
Classifier: Programming Language :: Python :: 3.5
Requires-Dist: Click (>=6.0)
